{"title":"GitHub Actions 实现 CI/CD 自动化部署","slug":"github-action-cicd","date":"2026-05-14T02:53:34.000Z","updated":"2026-07-05T02:00:07.043Z","comments":true,"path":"api/articles/github-action-cicd.json","realPath":null,"excerpt":null,"covers":null,"cover":null,"content":"<h2 id=\"概述\">概述</h2>\n<p>本文介绍如何使用 GitHub Actions 构建完整的 CI/CD 流水线，以实际项目为例，涵盖核心概念、配置实践、故障排查和优化建议。</p>\n<hr>\n<h2 id=\"一、CI-CD-概念解析\">一、CI/CD 概念解析</h2>\n<h3 id=\"1-1-核心定义\">1.1 核心定义</h3>\n<table>\n<thead>\n<tr>\n<th style=\"text-align:left\">概念</th>\n<th style=\"text-align:left\">定义</th>\n<th style=\"text-align:left\">核心职责</th>\n</tr>\n</thead>\n<tbody>\n<tr>\n<td style=\"text-align:left\"><strong>CI（持续集成）</strong></td>\n<td style=\"text-align:left\">代码提交后自动执行构建与测试</td>\n<td style=\"text-align:left\">代码质量保障、早期问题发现</td>\n</tr>\n<tr>\n<td style=\"text-align:left\"><strong>CD（持续部署）</strong></td>\n<td style=\"text-align:left\">构建产物自动部署到目标环境</td>\n<td style=\"text-align:left\">环境一致性、快速交付</td>\n</tr>\n</tbody>\n</table>\n<h3 id=\"1-2-典型工作流\">1.2 典型工作流</h3>\n<figure class=\"highlight plaintext\"><table><tr><td class=\"gutter\"><pre><span class=\"line\">1</span><br></pre></td><td class=\"code\"><pre><span class=\"line\">代码提交 → 触发事件 → 环境准备 → 依赖安装 → 测试执行 → 构建打包 → 部署发布</span><br></pre></td></tr></table></figure>\n<hr>\n<h2 id=\"二、GitHub-Actions-核心概念\">二、GitHub Actions 核心概念</h2>\n<h3 id=\"2-1-组件层次\">2.1 组件层次</h3>\n<figure class=\"highlight plaintext\"><table><tr><td class=\"gutter\"><pre><span class=\"line\">1</span><br><span class=\"line\">2</span><br><span class=\"line\">3</span><br><span class=\"line\">4</span><br><span class=\"line\">5</span><br></pre></td><td class=\"code\"><pre><span class=\"line\">Workflow（工作流）</span><br><span class=\"line\">    ├── Event（触发事件）</span><br><span class=\"line\">    └── Jobs（任务集合）</span><br><span class=\"line\">            └── Steps（步骤序列）</span><br><span class=\"line\">                    └── Actions（动作/命令）</span><br></pre></td></tr></table></figure>\n<h3 id=\"2-2-关键术语\">2.2 关键术语</h3>\n<ul>\n<li><strong>Workflow</strong>：定义在 <code>.github/workflows/*.yml</code>，描述完整的自动化流程</li>\n<li><strong>Event</strong>：触发条件，支持 <code>push</code>、<code>pull_request</code>、<code>schedule</code> 等</li>\n<li><strong>Job</strong>：独立运行单元，可配置并行或依赖关系</li>\n<li><strong>Step</strong>：Job 内的执行单元，支持脚本或复用 Actions</li>\n<li><strong>Runner</strong>：执行环境，支持 GitHub Hosted 或 Self-Hosted</li>\n</ul>\n<hr>\n<h2 id=\"三、实战配置：AI-项目-CI-CD-流水线\">三、实战配置：AI 项目 CI/CD 流水线</h2>\n<h3 id=\"3-1-目录结构\">3.1 目录结构</h3>\n<figure class=\"highlight plaintext\"><table><tr><td class=\"gutter\"><pre><span class=\"line\">1</span><br><span class=\"line\">2</span><br><span class=\"line\">3</span><br><span class=\"line\">4</span><br><span class=\"line\">5</span><br><span class=\"line\">6</span><br><span class=\"line\">7</span><br></pre></td><td class=\"code\"><pre><span class=\"line\">├── .github/</span><br><span class=\"line\">│   └── workflows/</span><br><span class=\"line\">│       └── main.yml          # 主工作流配置</span><br><span class=\"line\">├── src/                      # 源代码目录</span><br><span class=\"line\">├── tests/                    # 测试代码目录</span><br><span class=\"line\">├── Dockerfile                # 容器构建配置</span><br><span class=\"line\">└── requirements.txt          # Python 依赖声明</span><br></pre></td></tr></table></figure>\n<h3 id=\"3-2-完整配置示例\">3.2 完整配置示例</h3>\n<figure class=\"highlight yaml\"><table><tr><td class=\"gutter\"><pre><span class=\"line\">1</span><br><span class=\"line\">2</span><br><span class=\"line\">3</span><br><span class=\"line\">4</span><br><span class=\"line\">5</span><br><span class=\"line\">6</span><br><span class=\"line\">7</span><br><span class=\"line\">8</span><br><span class=\"line\">9</span><br><span class=\"line\">10</span><br><span class=\"line\">11</span><br><span class=\"line\">12</span><br><span class=\"line\">13</span><br><span class=\"line\">14</span><br><span class=\"line\">15</span><br><span class=\"line\">16</span><br><span class=\"line\">17</span><br><span class=\"line\">18</span><br><span class=\"line\">19</span><br><span class=\"line\">20</span><br><span class=\"line\">21</span><br><span class=\"line\">22</span><br><span class=\"line\">23</span><br><span class=\"line\">24</span><br><span class=\"line\">25</span><br><span class=\"line\">26</span><br><span class=\"line\">27</span><br><span class=\"line\">28</span><br><span class=\"line\">29</span><br><span class=\"line\">30</span><br><span class=\"line\">31</span><br><span class=\"line\">32</span><br><span class=\"line\">33</span><br><span class=\"line\">34</span><br><span class=\"line\">35</span><br><span class=\"line\">36</span><br><span class=\"line\">37</span><br><span class=\"line\">38</span><br><span class=\"line\">39</span><br><span class=\"line\">40</span><br><span class=\"line\">41</span><br><span class=\"line\">42</span><br><span class=\"line\">43</span><br><span class=\"line\">44</span><br><span class=\"line\">45</span><br><span class=\"line\">46</span><br><span class=\"line\">47</span><br><span class=\"line\">48</span><br><span class=\"line\">49</span><br><span class=\"line\">50</span><br><span class=\"line\">51</span><br><span class=\"line\">52</span><br><span class=\"line\">53</span><br><span class=\"line\">54</span><br><span class=\"line\">55</span><br><span class=\"line\">56</span><br><span class=\"line\">57</span><br><span class=\"line\">58</span><br><span class=\"line\">59</span><br><span class=\"line\">60</span><br><span class=\"line\">61</span><br></pre></td><td class=\"code\"><pre><span class=\"line\"><span class=\"attr\">name:</span> <span class=\"string\">AI-Project-CI</span></span><br><span class=\"line\"></span><br><span class=\"line\"><span class=\"attr\">on:</span></span><br><span class=\"line\">  <span class=\"attr\">push:</span></span><br><span class=\"line\">    <span class=\"attr\">branches:</span> [ <span class=\"string\">main</span>, <span class=\"string\">develop</span> ]</span><br><span class=\"line\">  <span class=\"attr\">pull_request:</span></span><br><span class=\"line\">    <span class=\"attr\">branches:</span> [ <span class=\"string\">main</span> ]</span><br><span class=\"line\"></span><br><span class=\"line\"><span class=\"attr\">jobs:</span></span><br><span class=\"line\">  <span class=\"attr\">build-and-test:</span></span><br><span class=\"line\">    <span class=\"attr\">runs-on:</span> <span class=\"string\">ubuntu-latest</span></span><br><span class=\"line\">    <span class=\"attr\">strategy:</span></span><br><span class=\"line\">      <span class=\"attr\">matrix:</span></span><br><span class=\"line\">        <span class=\"attr\">python-version:</span> [<span class=\"number\">3.9</span>, <span class=\"number\">3.10</span>]</span><br><span class=\"line\">    </span><br><span class=\"line\">    <span class=\"attr\">steps:</span></span><br><span class=\"line\">      <span class=\"bullet\">-</span> <span class=\"attr\">name:</span> <span class=\"string\">Checkout</span> <span class=\"string\">code</span></span><br><span class=\"line\">        <span class=\"attr\">uses:</span> <span class=\"string\">actions/checkout@v4</span></span><br><span class=\"line\">        <span class=\"attr\">with:</span></span><br><span class=\"line\">          <span class=\"attr\">fetch-depth:</span> <span class=\"number\">0</span></span><br><span class=\"line\"></span><br><span class=\"line\">      <span class=\"bullet\">-</span> <span class=\"attr\">name:</span> <span class=\"string\">Set</span> <span class=\"string\">up</span> <span class=\"string\">Python</span> <span class=\"string\">$&#123;&#123;</span> <span class=\"string\">matrix.python-version</span> <span class=\"string\">&#125;&#125;</span></span><br><span class=\"line\">        <span class=\"attr\">uses:</span> <span class=\"string\">actions/setup-python@v5</span></span><br><span class=\"line\">        <span class=\"attr\">with:</span></span><br><span class=\"line\">          <span class=\"attr\">python-version:</span> <span class=\"string\">$&#123;&#123;</span> <span class=\"string\">matrix.python-version</span> <span class=\"string\">&#125;&#125;</span></span><br><span class=\"line\">          <span class=\"attr\">cache:</span> <span class=\"string\">&#x27;pip&#x27;</span></span><br><span class=\"line\"></span><br><span class=\"line\">      <span class=\"bullet\">-</span> <span class=\"attr\">name:</span> <span class=\"string\">Install</span> <span class=\"string\">dependencies</span></span><br><span class=\"line\">        <span class=\"attr\">run:</span> <span class=\"string\">|</span></span><br><span class=\"line\"><span class=\"string\">          python -m pip install --upgrade pip</span></span><br><span class=\"line\"><span class=\"string\">          pip install -r requirements.txt</span></span><br><span class=\"line\"><span class=\"string\"></span></span><br><span class=\"line\">      <span class=\"bullet\">-</span> <span class=\"attr\">name:</span> <span class=\"string\">Run</span> <span class=\"string\">unit</span> <span class=\"string\">tests</span></span><br><span class=\"line\">        <span class=\"attr\">run:</span> <span class=\"string\">pytest</span> <span class=\"string\">tests/unit/</span> <span class=\"string\">-v</span> <span class=\"string\">--cov=src/</span></span><br><span class=\"line\"></span><br><span class=\"line\">      <span class=\"bullet\">-</span> <span class=\"attr\">name:</span> <span class=\"string\">Build</span> <span class=\"string\">Docker</span> <span class=\"string\">image</span></span><br><span class=\"line\">        <span class=\"attr\">if:</span> <span class=\"string\">github.ref</span> <span class=\"string\">==</span> <span class=\"string\">&#x27;refs/heads/main&#x27;</span></span><br><span class=\"line\">        <span class=\"attr\">run:</span> <span class=\"string\">|</span></span><br><span class=\"line\"><span class=\"string\">          docker build . -t $&#123;&#123; secrets.DOCKER_REGISTRY &#125;&#125;/anime-detect:$&#123;&#123; github.sha &#125;&#125;</span></span><br><span class=\"line\"><span class=\"string\">          docker login -u $&#123;&#123; secrets.DOCKER_USER &#125;&#125; -p $&#123;&#123; secrets.DOCKER_TOKEN &#125;&#125;</span></span><br><span class=\"line\"><span class=\"string\">          docker push $&#123;&#123; secrets.DOCKER_REGISTRY &#125;&#125;/anime-detect:$&#123;&#123; github.sha &#125;&#125;</span></span><br><span class=\"line\"><span class=\"string\"></span></span><br><span class=\"line\">  <span class=\"attr\">deploy:</span></span><br><span class=\"line\">    <span class=\"attr\">needs:</span> <span class=\"string\">build-and-test</span></span><br><span class=\"line\">    <span class=\"attr\">runs-on:</span> <span class=\"string\">ubuntu-latest</span></span><br><span class=\"line\">    <span class=\"attr\">if:</span> <span class=\"string\">github.ref</span> <span class=\"string\">==</span> <span class=\"string\">&#x27;refs/heads/main&#x27;</span></span><br><span class=\"line\">    </span><br><span class=\"line\">    <span class=\"attr\">steps:</span></span><br><span class=\"line\">      <span class=\"bullet\">-</span> <span class=\"attr\">name:</span> <span class=\"string\">Deploy</span> <span class=\"string\">to</span> <span class=\"string\">production</span></span><br><span class=\"line\">        <span class=\"attr\">uses:</span> <span class=\"string\">appleboy/ssh-action@v1.0.3</span></span><br><span class=\"line\">        <span class=\"attr\">with:</span></span><br><span class=\"line\">          <span class=\"attr\">host:</span> <span class=\"string\">$&#123;&#123;</span> <span class=\"string\">secrets.SSH_HOST</span> <span class=\"string\">&#125;&#125;</span></span><br><span class=\"line\">          <span class=\"attr\">username:</span> <span class=\"string\">$&#123;&#123;</span> <span class=\"string\">secrets.SSH_USER</span> <span class=\"string\">&#125;&#125;</span></span><br><span class=\"line\">          <span class=\"attr\">key:</span> <span class=\"string\">$&#123;&#123;</span> <span class=\"string\">secrets.SSH_PRIVATE_KEY</span> <span class=\"string\">&#125;&#125;</span></span><br><span class=\"line\">          <span class=\"attr\">script:</span> <span class=\"string\">|</span></span><br><span class=\"line\"><span class=\"string\">            docker pull $&#123;&#123; secrets.DOCKER_REGISTRY &#125;&#125;/anime-detect:$&#123;&#123; github.sha &#125;&#125;</span></span><br><span class=\"line\"><span class=\"string\">            docker stop anime-detect || true</span></span><br><span class=\"line\"><span class=\"string\">            docker rm anime-detect || true</span></span><br><span class=\"line\"><span class=\"string\">            docker run -d --name anime-detect -p 80:80 \\</span></span><br><span class=\"line\"><span class=\"string\">              -e REDIS_HOST=$&#123;&#123; secrets.REDIS_HOST &#125;&#125; \\</span></span><br><span class=\"line\"><span class=\"string\">              $&#123;&#123; secrets.DOCKER_REGISTRY &#125;&#125;/anime-detect:$&#123;&#123; github.sha &#125;&#125;</span></span><br></pre></td></tr></table></figure>\n<hr>\n<h2 id=\"四、常见问题与解决方案\">四、常见问题与解决方案</h2>\n<h3 id=\"4-1-依赖安装失败\">4.1 依赖安装失败</h3>\n<p><strong>问题现象</strong>：<code>libgl1-mesa-glx</code> 包无法安装</p>\n<p><strong>原因分析</strong>：Debian 12+ 版本中包名变更</p>\n<p><strong>解决方案</strong>：</p>\n<figure class=\"highlight dockerfile\"><table><tr><td class=\"gutter\"><pre><span class=\"line\">1</span><br><span class=\"line\">2</span><br><span class=\"line\">3</span><br><span class=\"line\">4</span><br><span class=\"line\">5</span><br><span class=\"line\">6</span><br><span class=\"line\">7</span><br><span class=\"line\">8</span><br><span class=\"line\">9</span><br><span class=\"line\">10</span><br><span class=\"line\">11</span><br><span class=\"line\">12</span><br></pre></td><td class=\"code\"><pre><span class=\"line\"><span class=\"comment\"># Dockerfile 正确配置</span></span><br><span class=\"line\"><span class=\"keyword\">FROM</span> python:<span class=\"number\">3.9</span>-slim</span><br><span class=\"line\"></span><br><span class=\"line\"><span class=\"keyword\">RUN</span><span class=\"language-bash\"> apt-get update &amp;&amp; apt-get install -y \\</span></span><br><span class=\"line\"><span class=\"language-bash\">    libgl1 \\</span></span><br><span class=\"line\"><span class=\"language-bash\">    libglib2.0-0 \\</span></span><br><span class=\"line\"><span class=\"language-bash\">    gcc \\</span></span><br><span class=\"line\"><span class=\"language-bash\">    &amp;&amp; <span class=\"built_in\">rm</span> -rf /var/lib/apt/lists/*</span></span><br><span class=\"line\"></span><br><span class=\"line\"><span class=\"keyword\">WORKDIR</span><span class=\"language-bash\"> /app</span></span><br><span class=\"line\"><span class=\"keyword\">COPY</span><span class=\"language-bash\"> requirements.txt .</span></span><br><span class=\"line\"><span class=\"keyword\">RUN</span><span class=\"language-bash\"> pip install --no-cache-dir -r requirements.txt</span></span><br></pre></td></tr></table></figure>\n<h3 id=\"4-2-敏感信息泄露\">4.2 敏感信息泄露</h3>\n<p><strong>问题现象</strong>：密码等敏感信息出现在日志中</p>\n<p><strong>解决方案</strong>：使用 GitHub Secrets 管理敏感数据</p>\n<figure class=\"highlight yaml\"><table><tr><td class=\"gutter\"><pre><span class=\"line\">1</span><br><span class=\"line\">2</span><br><span class=\"line\">3</span><br><span class=\"line\">4</span><br><span class=\"line\">5</span><br><span class=\"line\">6</span><br></pre></td><td class=\"code\"><pre><span class=\"line\"><span class=\"comment\"># 在 GitHub Secrets 中配置以下变量</span></span><br><span class=\"line\"><span class=\"comment\"># DOCKER_USER, DOCKER_TOKEN, SSH_HOST, SSH_USER, SSH_PRIVATE_KEY</span></span><br><span class=\"line\"></span><br><span class=\"line\"><span class=\"comment\"># 在 workflow 中引用</span></span><br><span class=\"line\"><span class=\"attr\">env:</span></span><br><span class=\"line\">  <span class=\"attr\">DATABASE_URL:</span> <span class=\"string\">$&#123;&#123;</span> <span class=\"string\">secrets.DATABASE_URL</span> <span class=\"string\">&#125;&#125;</span></span><br></pre></td></tr></table></figure>\n<h3 id=\"4-3-构建时间过长\">4.3 构建时间过长</h3>\n<p><strong>优化方案</strong>：启用缓存机制</p>\n<figure class=\"highlight yaml\"><table><tr><td class=\"gutter\"><pre><span class=\"line\">1</span><br><span class=\"line\">2</span><br><span class=\"line\">3</span><br><span class=\"line\">4</span><br><span class=\"line\">5</span><br><span class=\"line\">6</span><br><span class=\"line\">7</span><br><span class=\"line\">8</span><br><span class=\"line\">9</span><br></pre></td><td class=\"code\"><pre><span class=\"line\"><span class=\"bullet\">-</span> <span class=\"attr\">name:</span> <span class=\"string\">Cache</span> <span class=\"string\">pip</span> <span class=\"string\">dependencies</span></span><br><span class=\"line\">  <span class=\"attr\">uses:</span> <span class=\"string\">actions/cache@v4</span></span><br><span class=\"line\">  <span class=\"attr\">with:</span></span><br><span class=\"line\">    <span class=\"attr\">path:</span> <span class=\"string\">|</span></span><br><span class=\"line\"><span class=\"string\">      ~/.cache/pip</span></span><br><span class=\"line\"><span class=\"string\">      **/__pycache__</span></span><br><span class=\"line\"><span class=\"string\"></span>    <span class=\"attr\">key:</span> <span class=\"string\">$&#123;&#123;</span> <span class=\"string\">runner.os</span> <span class=\"string\">&#125;&#125;-python-$&#123;&#123;</span> <span class=\"string\">matrix.python-version</span> <span class=\"string\">&#125;&#125;-$&#123;&#123;</span> <span class=\"string\">hashFiles(&#x27;requirements.txt&#x27;)</span> <span class=\"string\">&#125;&#125;</span></span><br><span class=\"line\">    <span class=\"attr\">restore-keys:</span> <span class=\"string\">|</span></span><br><span class=\"line\">      <span class=\"string\">$&#123;&#123;</span> <span class=\"string\">runner.os</span> <span class=\"string\">&#125;&#125;-python-$&#123;&#123;</span> <span class=\"string\">matrix.python-version</span> <span class=\"string\">&#125;&#125;-</span></span><br></pre></td></tr></table></figure>\n<hr>\n<h2 id=\"五、日志分析与调试\">五、日志分析与调试</h2>\n<h3 id=\"5-1-日志访问路径\">5.1 日志访问路径</h3>\n<figure class=\"highlight plaintext\"><table><tr><td class=\"gutter\"><pre><span class=\"line\">1</span><br></pre></td><td class=\"code\"><pre><span class=\"line\">GitHub Repository → Actions → 选择 Workflow → 选择 Run → 查看 Job 日志</span><br></pre></td></tr></table></figure>\n<h3 id=\"5-2-常见错误码\">5.2 常见错误码</h3>\n<table>\n<thead>\n<tr>\n<th style=\"text-align:left\">错误码</th>\n<th style=\"text-align:left\">含义</th>\n<th style=\"text-align:left\">排查方向</th>\n</tr>\n</thead>\n<tbody>\n<tr>\n<td style=\"text-align:left\"><code>exit code 1</code></td>\n<td style=\"text-align:left\">命令执行失败</td>\n<td style=\"text-align:left\">检查脚本语法和依赖</td>\n</tr>\n<tr>\n<td style=\"text-align:left\"><code>exit code 137</code></td>\n<td style=\"text-align:left\">内存不足</td>\n<td style=\"text-align:left\">增加 Runner 资源或优化代码</td>\n</tr>\n<tr>\n<td style=\"text-align:left\"><code>Connection refused</code></td>\n<td style=\"text-align:left\">网络连接失败</td>\n<td style=\"text-align:left\">检查网络策略和目标服务状态</td>\n</tr>\n</tbody>\n</table>\n<h3 id=\"5-3-调试技巧\">5.3 调试技巧</h3>\n<ol>\n<li>使用 <code>set -x</code> 启用命令调试</li>\n<li>添加 <code>echo</code> 输出关键变量值</li>\n<li>使用 <code>tmate</code> 进行交互式调试</li>\n</ol>\n<hr>\n<h2 id=\"六、运行效果示例\">六、运行效果示例</h2>\n<h3 id=\"6-1-成功执行效果\">6.1 成功执行效果</h3>\n<p>当工作流成功执行时，GitHub Actions 会显示以下状态：</p>\n<p><strong>Actions 页面概览</strong>：</p>\n<figure class=\"highlight plaintext\"><table><tr><td class=\"gutter\"><pre><span class=\"line\">1</span><br><span class=\"line\">2</span><br><span class=\"line\">3</span><br><span class=\"line\">4</span><br><span class=\"line\">5</span><br><span class=\"line\">6</span><br><span class=\"line\">7</span><br><span class=\"line\">8</span><br></pre></td><td class=\"code\"><pre><span class=\"line\">✓ AI-Project-CI</span><br><span class=\"line\">  push · main</span><br><span class=\"line\">  1 hour ago · in 2m 35s</span><br><span class=\"line\">  </span><br><span class=\"line\">  Jobs:</span><br><span class=\"line\">    ✅ build-and-test (Python 3.9)</span><br><span class=\"line\">    ✅ build-and-test (Python 3.10)  </span><br><span class=\"line\">    ✅ deploy</span><br></pre></td></tr></table></figure>\n<p><strong>测试步骤输出示例</strong>：</p>\n<figure class=\"highlight plaintext\"><table><tr><td class=\"gutter\"><pre><span class=\"line\">1</span><br><span class=\"line\">2</span><br><span class=\"line\">3</span><br><span class=\"line\">4</span><br><span class=\"line\">5</span><br><span class=\"line\">6</span><br><span class=\"line\">7</span><br><span class=\"line\">8</span><br><span class=\"line\">9</span><br><span class=\"line\">10</span><br><span class=\"line\">11</span><br><span class=\"line\">12</span><br><span class=\"line\">13</span><br><span class=\"line\">14</span><br><span class=\"line\">15</span><br><span class=\"line\">16</span><br><span class=\"line\">17</span><br><span class=\"line\">18</span><br><span class=\"line\">19</span><br><span class=\"line\">20</span><br><span class=\"line\">21</span><br><span class=\"line\">22</span><br><span class=\"line\">23</span><br></pre></td><td class=\"code\"><pre><span class=\"line\">Run pytest tests/unit/ -v --cov=src/</span><br><span class=\"line\">============================= test session starts ==============================</span><br><span class=\"line\">platform linux -- Python 3.9.17, pytest-7.4.0, pluggy</span><br><span class=\"line\">rootdir: /home/runner/work/anime-detect/anime-detect</span><br><span class=\"line\">collected 24 items</span><br><span class=\"line\"></span><br><span class=\"line\">tests/unit/test_detect.py::test_load_model PASSED                       [  4%]</span><br><span class=\"line\">tests/unit/test_detect.py::test_image_preprocess PASSED                  [  8%]</span><br><span class=\"line\">tests/unit/test_detect.py::test_detect_anime PASSED                      [ 12%]</span><br><span class=\"line\">...</span><br><span class=\"line\">tests/unit/test_api.py::test_health_check PASSED                         [ 95%]</span><br><span class=\"line\">tests/unit/test_api.py::test_inference_endpoint PASSED                   [100%]</span><br><span class=\"line\"></span><br><span class=\"line\">---------- coverage: platform linux, python 3.9.17-final-0 ----------</span><br><span class=\"line\">Name                      Stmts   Miss  Cover</span><br><span class=\"line\">---------------------------------------------</span><br><span class=\"line\">src/detect.py               120      5    96%</span><br><span class=\"line\">src/api.py                   85      3    96%</span><br><span class=\"line\">src/utils.py                 45      0   100%</span><br><span class=\"line\">---------------------------------------------</span><br><span class=\"line\">TOTAL                       250      8    97%</span><br><span class=\"line\"></span><br><span class=\"line\">============================= 24 passed in 15.23s ==============================</span><br></pre></td></tr></table></figure>\n<p><strong>Docker 构建输出示例</strong>：</p>\n<figure class=\"highlight plaintext\"><table><tr><td class=\"gutter\"><pre><span class=\"line\">1</span><br><span class=\"line\">2</span><br><span class=\"line\">3</span><br><span class=\"line\">4</span><br><span class=\"line\">5</span><br><span class=\"line\">6</span><br><span class=\"line\">7</span><br><span class=\"line\">8</span><br><span class=\"line\">9</span><br><span class=\"line\">10</span><br><span class=\"line\">11</span><br><span class=\"line\">12</span><br><span class=\"line\">13</span><br><span class=\"line\">14</span><br><span class=\"line\">15</span><br><span class=\"line\">16</span><br><span class=\"line\">17</span><br><span class=\"line\">18</span><br><span class=\"line\">19</span><br><span class=\"line\">20</span><br><span class=\"line\">21</span><br></pre></td><td class=\"code\"><pre><span class=\"line\">Run docker build . -t registry.example.com/anime-detect:abc123</span><br><span class=\"line\">Sending build context to Docker daemon  156.2MB</span><br><span class=\"line\"></span><br><span class=\"line\">Step 1/6 : FROM python:3.9-slim</span><br><span class=\"line\"> ---&gt; 8a955d570e80</span><br><span class=\"line\">Step 2/6 : RUN apt-get update &amp;&amp; apt-get install -y libgl1 libglib2.0-0 gcc</span><br><span class=\"line\"> ---&gt; Using cache</span><br><span class=\"line\"> ---&gt; abc123456789</span><br><span class=\"line\">Step 3/6 : WORKDIR /app</span><br><span class=\"line\"> ---&gt; Using cache</span><br><span class=\"line\"> ---&gt; def098765432</span><br><span class=\"line\">Step 4/6 : COPY requirements.txt .</span><br><span class=\"line\"> ---&gt; Using cache</span><br><span class=\"line\"> ---&gt; 123456789abc</span><br><span class=\"line\">Step 5/6 : RUN pip install --no-cache-dir -r requirements.txt</span><br><span class=\"line\"> ---&gt; Using cache</span><br><span class=\"line\"> ---&gt; 987654321def</span><br><span class=\"line\">Step 6/6 : COPY . .</span><br><span class=\"line\"> ---&gt; 0123456789ab</span><br><span class=\"line\">Successfully built 0123456789ab</span><br><span class=\"line\">Successfully tagged registry.example.com/anime-detect:abc123</span><br></pre></td></tr></table></figure>\n<h3 id=\"6-2-失败执行效果\">6.2 失败执行效果</h3>\n<p><strong>测试失败示例</strong>：</p>\n<figure class=\"highlight plaintext\"><table><tr><td class=\"gutter\"><pre><span class=\"line\">1</span><br><span class=\"line\">2</span><br><span class=\"line\">3</span><br><span class=\"line\">4</span><br><span class=\"line\">5</span><br><span class=\"line\">6</span><br><span class=\"line\">7</span><br><span class=\"line\">8</span><br><span class=\"line\">9</span><br><span class=\"line\">10</span><br><span class=\"line\">11</span><br><span class=\"line\">12</span><br><span class=\"line\">13</span><br><span class=\"line\">14</span><br><span class=\"line\">15</span><br><span class=\"line\">16</span><br><span class=\"line\">17</span><br><span class=\"line\">18</span><br></pre></td><td class=\"code\"><pre><span class=\"line\">Run pytest tests/unit/ -v --cov=src/</span><br><span class=\"line\">...</span><br><span class=\"line\">tests/unit/test_detect.py::test_detect_anime FAILED                     [ 12%]</span><br><span class=\"line\"></span><br><span class=\"line\">=================================== FAILURES ===================================</span><br><span class=\"line\">___________________________ test_detect_anime ___________________________</span><br><span class=\"line\"></span><br><span class=\"line\">def test_detect_anime():</span><br><span class=\"line\">    model = load_model()</span><br><span class=\"line\">    result = model.predict(test_image)</span><br><span class=\"line\">    </span><br><span class=\"line\">&gt;   assert result[&#x27;confidence&#x27;] &gt; 0.9</span><br><span class=\"line\">E   AssertionError: assert 0.85 &gt; 0.9</span><br><span class=\"line\">E    +  where 0.85 = &#123;&#x27;label&#x27;: &#x27;Sailor Moon&#x27;, &#x27;confidence&#x27;: 0.85&#125;[&#x27;confidence&#x27;]</span><br><span class=\"line\"></span><br><span class=\"line\">tests/unit/test_detect.py:23: AssertionError</span><br><span class=\"line\">============================= 1 failed, 23 passed in 14.87s ======================</span><br><span class=\"line\">Error: Process completed with exit code 1</span><br></pre></td></tr></table></figure>\n<p><strong>依赖安装失败示例</strong>：</p>\n<figure class=\"highlight plaintext\"><table><tr><td class=\"gutter\"><pre><span class=\"line\">1</span><br><span class=\"line\">2</span><br><span class=\"line\">3</span><br><span class=\"line\">4</span><br><span class=\"line\">5</span><br><span class=\"line\">6</span><br><span class=\"line\">7</span><br><span class=\"line\">8</span><br><span class=\"line\">9</span><br><span class=\"line\">10</span><br><span class=\"line\">11</span><br><span class=\"line\">12</span><br><span class=\"line\">13</span><br><span class=\"line\">14</span><br><span class=\"line\">15</span><br><span class=\"line\">16</span><br><span class=\"line\">17</span><br><span class=\"line\">18</span><br><span class=\"line\">19</span><br><span class=\"line\">20</span><br></pre></td><td class=\"code\"><pre><span class=\"line\">Run pip install -r requirements.txt</span><br><span class=\"line\">Collecting torch==2.0.1</span><br><span class=\"line\">  Downloading torch-2.0.1-cp39-none-linux_x86_64.whl (172.3 MB)</span><br><span class=\"line\">     ━━━━━━━━━━━━━━━━━━━━━━━━━━━━━━━━━━━━━━━━━━━━━━━━━━━━ 172.3/172.3 MB 45.2 MB/s</span><br><span class=\"line\">Collecting opencv-python==4.7.0.72</span><br><span class=\"line\">  Downloading opencv-python-4.7.0.72.tar.gz (88.3 MB)</span><br><span class=\"line\">     ━━━━━━━━━━━━━━━━━━━━━━━━━━━━━━━━━━━━━━━━━━━━━━━━━━━━ 88.3/88.3 MB 42.1 MB/s</span><br><span class=\"line\">  Installing build dependencies ... done</span><br><span class=\"line\">  Getting requirements to build wheel ... done</span><br><span class=\"line\">  Preparing metadata (pyproject.toml) ... error</span><br><span class=\"line\">  error: subprocess-exited-with-error</span><br><span class=\"line\">  </span><br><span class=\"line\">  × Preparing metadata (pyproject.toml) did not run successfully.</span><br><span class=\"line\">  │ exit code: 1</span><br><span class=\"line\">  ╰─&gt; [55 lines of output]</span><br><span class=\"line\">      error: OpenCV requires &#x27;numpy&gt;=1.21.2&#x27; but you have numpy 1.19.5 installed.</span><br><span class=\"line\">      [end of output]</span><br><span class=\"line\">  </span><br><span class=\"line\">  note: This error originates from a subprocess, and is likely not a problem with pip.</span><br><span class=\"line\">Error: Process completed with exit code 1</span><br></pre></td></tr></table></figure>\n<h3 id=\"6-3-时间统计示例\">6.3 时间统计示例</h3>\n<table>\n<thead>\n<tr>\n<th style=\"text-align:left\">步骤</th>\n<th style=\"text-align:left\">耗时</th>\n<th style=\"text-align:left\">状态</th>\n</tr>\n</thead>\n<tbody>\n<tr>\n<td style=\"text-align:left\">Checkout code</td>\n<td style=\"text-align:left\">15s</td>\n<td style=\"text-align:left\">✅</td>\n</tr>\n<tr>\n<td style=\"text-align:left\">Set up Python</td>\n<td style=\"text-align:left\">8s</td>\n<td style=\"text-align:left\">✅</td>\n</tr>\n<tr>\n<td style=\"text-align:left\">Install dependencies</td>\n<td style=\"text-align:left\">45s</td>\n<td style=\"text-align:left\">✅</td>\n</tr>\n<tr>\n<td style=\"text-align:left\">Run unit tests</td>\n<td style=\"text-align:left\">1min 20s</td>\n<td style=\"text-align:left\">✅</td>\n</tr>\n<tr>\n<td style=\"text-align:left\">Build Docker image</td>\n<td style=\"text-align:left\">3min 10s</td>\n<td style=\"text-align:left\">✅</td>\n</tr>\n<tr>\n<td style=\"text-align:left\">Deploy to production</td>\n<td style=\"text-align:left\">45s</td>\n<td style=\"text-align:left\">✅</td>\n</tr>\n<tr>\n<td style=\"text-align:left\"><strong>总计</strong></td>\n<td style=\"text-align:left\"><strong>5min 43s</strong></td>\n<td style=\"text-align:left\"><strong>✅</strong></td>\n</tr>\n</tbody>\n</table>\n<hr>\n<h2 id=\"七、进阶配置\">七、进阶配置</h2>\n<h3 id=\"7-1-多环境部署\">7.1 多环境部署</h3>\n<figure class=\"highlight yaml\"><table><tr><td class=\"gutter\"><pre><span class=\"line\">1</span><br><span class=\"line\">2</span><br><span class=\"line\">3</span><br><span class=\"line\">4</span><br><span class=\"line\">5</span><br><span class=\"line\">6</span><br><span class=\"line\">7</span><br><span class=\"line\">8</span><br><span class=\"line\">9</span><br><span class=\"line\">10</span><br><span class=\"line\">11</span><br><span class=\"line\">12</span><br></pre></td><td class=\"code\"><pre><span class=\"line\"><span class=\"attr\">jobs:</span></span><br><span class=\"line\">  <span class=\"attr\">deploy-staging:</span></span><br><span class=\"line\">    <span class=\"attr\">runs-on:</span> <span class=\"string\">ubuntu-latest</span></span><br><span class=\"line\">    <span class=\"attr\">environment:</span> <span class=\"string\">staging</span></span><br><span class=\"line\">    <span class=\"attr\">steps:</span> [<span class=\"string\">...</span>]</span><br><span class=\"line\"></span><br><span class=\"line\">  <span class=\"attr\">deploy-production:</span></span><br><span class=\"line\">    <span class=\"attr\">needs:</span> <span class=\"string\">deploy-staging</span></span><br><span class=\"line\">    <span class=\"attr\">runs-on:</span> <span class=\"string\">ubuntu-latest</span></span><br><span class=\"line\">    <span class=\"attr\">environment:</span> <span class=\"string\">production</span></span><br><span class=\"line\">    <span class=\"attr\">environment_url:</span> <span class=\"string\">https://api.example.com</span></span><br><span class=\"line\">    <span class=\"attr\">steps:</span> [<span class=\"string\">...</span>]</span><br></pre></td></tr></table></figure>\n<h3 id=\"6-2-定时任务\">6.2 定时任务</h3>\n<figure class=\"highlight yaml\"><table><tr><td class=\"gutter\"><pre><span class=\"line\">1</span><br><span class=\"line\">2</span><br><span class=\"line\">3</span><br></pre></td><td class=\"code\"><pre><span class=\"line\"><span class=\"attr\">on:</span></span><br><span class=\"line\">  <span class=\"attr\">schedule:</span></span><br><span class=\"line\">    <span class=\"bullet\">-</span> <span class=\"attr\">cron:</span> <span class=\"string\">&#x27;0 2 * * *&#x27;</span>  <span class=\"comment\"># 每天凌晨 2 点执行</span></span><br></pre></td></tr></table></figure>\n<h3 id=\"6-3-矩阵构建\">6.3 矩阵构建</h3>\n<figure class=\"highlight yaml\"><table><tr><td class=\"gutter\"><pre><span class=\"line\">1</span><br><span class=\"line\">2</span><br><span class=\"line\">3</span><br><span class=\"line\">4</span><br></pre></td><td class=\"code\"><pre><span class=\"line\"><span class=\"attr\">strategy:</span></span><br><span class=\"line\">  <span class=\"attr\">matrix:</span></span><br><span class=\"line\">    <span class=\"attr\">os:</span> [<span class=\"string\">ubuntu-latest</span>, <span class=\"string\">windows-latest</span>]</span><br><span class=\"line\">    <span class=\"attr\">python-version:</span> [<span class=\"string\">&quot;3.9&quot;</span>, <span class=\"string\">&quot;3.10&quot;</span>, <span class=\"string\">&quot;3.11&quot;</span>]</span><br></pre></td></tr></table></figure>\n<hr>\n<h2 id=\"七、最佳实践\">七、最佳实践</h2>\n<ol>\n<li><strong>分层设计</strong>：将测试、构建、部署分离为独立 Job</li>\n<li><strong>环境隔离</strong>：使用 Environment 功能管理不同部署环境</li>\n<li><strong>安全优先</strong>：所有敏感信息通过 Secrets 管理</li>\n<li><strong>缓存优化</strong>：合理使用缓存减少重复操作</li>\n<li><strong>失败通知</strong>：配置 Slack/钉钉等即时通知</li>\n<li><strong>权限最小化</strong>：限制 GitHub Token 权限范围</li>\n</ol>\n<hr>\n<h2 id=\"总结\">总结</h2>\n<p>GitHub Actions 提供了强大的自动化能力，通过合理配置可以实现从代码提交到生产部署的全流程自动化。关键在于理解组件模型、掌握配置语法，并结合项目特点进行优化。</p>\n<hr>\n<p>参考链接：</p>\n<ul>\n<li><a href=\"https://docs.github.com/en/actions\">GitHub Actions 官方文档</a></li>\n<li><a href=\"https://github.com/marketplace?type=actions\">GitHub Actions 市场</a></li>\n</ul>\n","more":"<h2 id=\"概述\">概述</h2>\n<p>本文介绍如何使用 GitHub Actions 构建完整的 CI/CD 流水线，以实际项目为例，涵盖核心概念、配置实践、故障排查和优化建议。</p>\n<hr>\n<h2 id=\"一、CI-CD-概念解析\">一、CI/CD 概念解析</h2>\n<h3 id=\"1-1-核心定义\">1.1 核心定义</h3>\n<table>\n<thead>\n<tr>\n<th style=\"text-align:left\">概念</th>\n<th style=\"text-align:left\">定义</th>\n<th style=\"text-align:left\">核心职责</th>\n</tr>\n</thead>\n<tbody>\n<tr>\n<td style=\"text-align:left\"><strong>CI（持续集成）</strong></td>\n<td style=\"text-align:left\">代码提交后自动执行构建与测试</td>\n<td style=\"text-align:left\">代码质量保障、早期问题发现</td>\n</tr>\n<tr>\n<td style=\"text-align:left\"><strong>CD（持续部署）</strong></td>\n<td style=\"text-align:left\">构建产物自动部署到目标环境</td>\n<td style=\"text-align:left\">环境一致性、快速交付</td>\n</tr>\n</tbody>\n</table>\n<h3 id=\"1-2-典型工作流\">1.2 典型工作流</h3>\n<figure class=\"highlight plaintext\"><table><tr><td class=\"gutter\"><pre><span class=\"line\">1</span><br></pre></td><td class=\"code\"><pre><span class=\"line\">代码提交 → 触发事件 → 环境准备 → 依赖安装 → 测试执行 → 构建打包 → 部署发布</span><br></pre></td></tr></table></figure>\n<hr>\n<h2 id=\"二、GitHub-Actions-核心概念\">二、GitHub Actions 核心概念</h2>\n<h3 id=\"2-1-组件层次\">2.1 组件层次</h3>\n<figure class=\"highlight plaintext\"><table><tr><td class=\"gutter\"><pre><span class=\"line\">1</span><br><span class=\"line\">2</span><br><span class=\"line\">3</span><br><span class=\"line\">4</span><br><span class=\"line\">5</span><br></pre></td><td class=\"code\"><pre><span class=\"line\">Workflow（工作流）</span><br><span class=\"line\">    ├── Event（触发事件）</span><br><span class=\"line\">    └── Jobs（任务集合）</span><br><span class=\"line\">            └── Steps（步骤序列）</span><br><span class=\"line\">                    └── Actions（动作/命令）</span><br></pre></td></tr></table></figure>\n<h3 id=\"2-2-关键术语\">2.2 关键术语</h3>\n<ul>\n<li><strong>Workflow</strong>：定义在 <code>.github/workflows/*.yml</code>，描述完整的自动化流程</li>\n<li><strong>Event</strong>：触发条件，支持 <code>push</code>、<code>pull_request</code>、<code>schedule</code> 等</li>\n<li><strong>Job</strong>：独立运行单元，可配置并行或依赖关系</li>\n<li><strong>Step</strong>：Job 内的执行单元，支持脚本或复用 Actions</li>\n<li><strong>Runner</strong>：执行环境，支持 GitHub Hosted 或 Self-Hosted</li>\n</ul>\n<hr>\n<h2 id=\"三、实战配置：AI-项目-CI-CD-流水线\">三、实战配置：AI 项目 CI/CD 流水线</h2>\n<h3 id=\"3-1-目录结构\">3.1 目录结构</h3>\n<figure class=\"highlight plaintext\"><table><tr><td class=\"gutter\"><pre><span class=\"line\">1</span><br><span class=\"line\">2</span><br><span class=\"line\">3</span><br><span class=\"line\">4</span><br><span class=\"line\">5</span><br><span class=\"line\">6</span><br><span class=\"line\">7</span><br></pre></td><td class=\"code\"><pre><span class=\"line\">├── .github/</span><br><span class=\"line\">│   └── workflows/</span><br><span class=\"line\">│       └── main.yml          # 主工作流配置</span><br><span class=\"line\">├── src/                      # 源代码目录</span><br><span class=\"line\">├── tests/                    # 测试代码目录</span><br><span class=\"line\">├── Dockerfile                # 容器构建配置</span><br><span class=\"line\">└── requirements.txt          # Python 依赖声明</span><br></pre></td></tr></table></figure>\n<h3 id=\"3-2-完整配置示例\">3.2 完整配置示例</h3>\n<figure class=\"highlight yaml\"><table><tr><td class=\"gutter\"><pre><span class=\"line\">1</span><br><span class=\"line\">2</span><br><span class=\"line\">3</span><br><span class=\"line\">4</span><br><span class=\"line\">5</span><br><span class=\"line\">6</span><br><span class=\"line\">7</span><br><span class=\"line\">8</span><br><span class=\"line\">9</span><br><span class=\"line\">10</span><br><span class=\"line\">11</span><br><span class=\"line\">12</span><br><span class=\"line\">13</span><br><span class=\"line\">14</span><br><span class=\"line\">15</span><br><span class=\"line\">16</span><br><span class=\"line\">17</span><br><span class=\"line\">18</span><br><span class=\"line\">19</span><br><span class=\"line\">20</span><br><span class=\"line\">21</span><br><span class=\"line\">22</span><br><span class=\"line\">23</span><br><span class=\"line\">24</span><br><span class=\"line\">25</span><br><span class=\"line\">26</span><br><span class=\"line\">27</span><br><span class=\"line\">28</span><br><span class=\"line\">29</span><br><span class=\"line\">30</span><br><span class=\"line\">31</span><br><span class=\"line\">32</span><br><span class=\"line\">33</span><br><span class=\"line\">34</span><br><span class=\"line\">35</span><br><span class=\"line\">36</span><br><span class=\"line\">37</span><br><span class=\"line\">38</span><br><span class=\"line\">39</span><br><span class=\"line\">40</span><br><span class=\"line\">41</span><br><span class=\"line\">42</span><br><span class=\"line\">43</span><br><span class=\"line\">44</span><br><span class=\"line\">45</span><br><span class=\"line\">46</span><br><span class=\"line\">47</span><br><span class=\"line\">48</span><br><span class=\"line\">49</span><br><span class=\"line\">50</span><br><span class=\"line\">51</span><br><span class=\"line\">52</span><br><span class=\"line\">53</span><br><span class=\"line\">54</span><br><span class=\"line\">55</span><br><span class=\"line\">56</span><br><span class=\"line\">57</span><br><span class=\"line\">58</span><br><span class=\"line\">59</span><br><span class=\"line\">60</span><br><span class=\"line\">61</span><br></pre></td><td class=\"code\"><pre><span class=\"line\"><span class=\"attr\">name:</span> <span class=\"string\">AI-Project-CI</span></span><br><span class=\"line\"></span><br><span class=\"line\"><span class=\"attr\">on:</span></span><br><span class=\"line\">  <span class=\"attr\">push:</span></span><br><span class=\"line\">    <span class=\"attr\">branches:</span> [ <span class=\"string\">main</span>, <span class=\"string\">develop</span> ]</span><br><span class=\"line\">  <span class=\"attr\">pull_request:</span></span><br><span class=\"line\">    <span class=\"attr\">branches:</span> [ <span class=\"string\">main</span> ]</span><br><span class=\"line\"></span><br><span class=\"line\"><span class=\"attr\">jobs:</span></span><br><span class=\"line\">  <span class=\"attr\">build-and-test:</span></span><br><span class=\"line\">    <span class=\"attr\">runs-on:</span> <span class=\"string\">ubuntu-latest</span></span><br><span class=\"line\">    <span class=\"attr\">strategy:</span></span><br><span class=\"line\">      <span class=\"attr\">matrix:</span></span><br><span class=\"line\">        <span class=\"attr\">python-version:</span> [<span class=\"number\">3.9</span>, <span class=\"number\">3.10</span>]</span><br><span class=\"line\">    </span><br><span class=\"line\">    <span class=\"attr\">steps:</span></span><br><span class=\"line\">      <span class=\"bullet\">-</span> <span class=\"attr\">name:</span> <span class=\"string\">Checkout</span> <span class=\"string\">code</span></span><br><span class=\"line\">        <span class=\"attr\">uses:</span> <span class=\"string\">actions/checkout@v4</span></span><br><span class=\"line\">        <span class=\"attr\">with:</span></span><br><span class=\"line\">          <span class=\"attr\">fetch-depth:</span> <span class=\"number\">0</span></span><br><span class=\"line\"></span><br><span class=\"line\">      <span class=\"bullet\">-</span> <span class=\"attr\">name:</span> <span class=\"string\">Set</span> <span class=\"string\">up</span> <span class=\"string\">Python</span> <span class=\"string\">$&#123;&#123;</span> <span class=\"string\">matrix.python-version</span> <span class=\"string\">&#125;&#125;</span></span><br><span class=\"line\">        <span class=\"attr\">uses:</span> <span class=\"string\">actions/setup-python@v5</span></span><br><span class=\"line\">        <span class=\"attr\">with:</span></span><br><span class=\"line\">          <span class=\"attr\">python-version:</span> <span class=\"string\">$&#123;&#123;</span> <span class=\"string\">matrix.python-version</span> <span class=\"string\">&#125;&#125;</span></span><br><span class=\"line\">          <span class=\"attr\">cache:</span> <span class=\"string\">&#x27;pip&#x27;</span></span><br><span class=\"line\"></span><br><span class=\"line\">      <span class=\"bullet\">-</span> <span class=\"attr\">name:</span> <span class=\"string\">Install</span> <span class=\"string\">dependencies</span></span><br><span class=\"line\">        <span class=\"attr\">run:</span> <span class=\"string\">|</span></span><br><span class=\"line\"><span class=\"string\">          python -m pip install --upgrade pip</span></span><br><span class=\"line\"><span class=\"string\">          pip install -r requirements.txt</span></span><br><span class=\"line\"><span class=\"string\"></span></span><br><span class=\"line\">      <span class=\"bullet\">-</span> <span class=\"attr\">name:</span> <span class=\"string\">Run</span> <span class=\"string\">unit</span> <span class=\"string\">tests</span></span><br><span class=\"line\">        <span class=\"attr\">run:</span> <span class=\"string\">pytest</span> <span class=\"string\">tests/unit/</span> <span class=\"string\">-v</span> <span class=\"string\">--cov=src/</span></span><br><span class=\"line\"></span><br><span class=\"line\">      <span class=\"bullet\">-</span> <span class=\"attr\">name:</span> <span class=\"string\">Build</span> <span class=\"string\">Docker</span> <span class=\"string\">image</span></span><br><span class=\"line\">        <span class=\"attr\">if:</span> <span class=\"string\">github.ref</span> <span class=\"string\">==</span> <span class=\"string\">&#x27;refs/heads/main&#x27;</span></span><br><span class=\"line\">        <span class=\"attr\">run:</span> <span class=\"string\">|</span></span><br><span class=\"line\"><span class=\"string\">          docker build . -t $&#123;&#123; secrets.DOCKER_REGISTRY &#125;&#125;/anime-detect:$&#123;&#123; github.sha &#125;&#125;</span></span><br><span class=\"line\"><span class=\"string\">          docker login -u $&#123;&#123; secrets.DOCKER_USER &#125;&#125; -p $&#123;&#123; secrets.DOCKER_TOKEN &#125;&#125;</span></span><br><span class=\"line\"><span class=\"string\">          docker push $&#123;&#123; secrets.DOCKER_REGISTRY &#125;&#125;/anime-detect:$&#123;&#123; github.sha &#125;&#125;</span></span><br><span class=\"line\"><span class=\"string\"></span></span><br><span class=\"line\">  <span class=\"attr\">deploy:</span></span><br><span class=\"line\">    <span class=\"attr\">needs:</span> <span class=\"string\">build-and-test</span></span><br><span class=\"line\">    <span class=\"attr\">runs-on:</span> <span class=\"string\">ubuntu-latest</span></span><br><span class=\"line\">    <span class=\"attr\">if:</span> <span class=\"string\">github.ref</span> <span class=\"string\">==</span> <span class=\"string\">&#x27;refs/heads/main&#x27;</span></span><br><span class=\"line\">    </span><br><span class=\"line\">    <span class=\"attr\">steps:</span></span><br><span class=\"line\">      <span class=\"bullet\">-</span> <span class=\"attr\">name:</span> <span class=\"string\">Deploy</span> <span class=\"string\">to</span> <span class=\"string\">production</span></span><br><span class=\"line\">        <span class=\"attr\">uses:</span> <span class=\"string\">appleboy/ssh-action@v1.0.3</span></span><br><span class=\"line\">        <span class=\"attr\">with:</span></span><br><span class=\"line\">          <span class=\"attr\">host:</span> <span class=\"string\">$&#123;&#123;</span> <span class=\"string\">secrets.SSH_HOST</span> <span class=\"string\">&#125;&#125;</span></span><br><span class=\"line\">          <span class=\"attr\">username:</span> <span class=\"string\">$&#123;&#123;</span> <span class=\"string\">secrets.SSH_USER</span> <span class=\"string\">&#125;&#125;</span></span><br><span class=\"line\">          <span class=\"attr\">key:</span> <span class=\"string\">$&#123;&#123;</span> <span class=\"string\">secrets.SSH_PRIVATE_KEY</span> <span class=\"string\">&#125;&#125;</span></span><br><span class=\"line\">          <span class=\"attr\">script:</span> <span class=\"string\">|</span></span><br><span class=\"line\"><span class=\"string\">            docker pull $&#123;&#123; secrets.DOCKER_REGISTRY &#125;&#125;/anime-detect:$&#123;&#123; github.sha &#125;&#125;</span></span><br><span class=\"line\"><span class=\"string\">            docker stop anime-detect || true</span></span><br><span class=\"line\"><span class=\"string\">            docker rm anime-detect || true</span></span><br><span class=\"line\"><span class=\"string\">            docker run -d --name anime-detect -p 80:80 \\</span></span><br><span class=\"line\"><span class=\"string\">              -e REDIS_HOST=$&#123;&#123; secrets.REDIS_HOST &#125;&#125; \\</span></span><br><span class=\"line\"><span class=\"string\">              $&#123;&#123; secrets.DOCKER_REGISTRY &#125;&#125;/anime-detect:$&#123;&#123; github.sha &#125;&#125;</span></span><br></pre></td></tr></table></figure>\n<hr>\n<h2 id=\"四、常见问题与解决方案\">四、常见问题与解决方案</h2>\n<h3 id=\"4-1-依赖安装失败\">4.1 依赖安装失败</h3>\n<p><strong>问题现象</strong>：<code>libgl1-mesa-glx</code> 包无法安装</p>\n<p><strong>原因分析</strong>：Debian 12+ 版本中包名变更</p>\n<p><strong>解决方案</strong>：</p>\n<figure class=\"highlight dockerfile\"><table><tr><td class=\"gutter\"><pre><span class=\"line\">1</span><br><span class=\"line\">2</span><br><span class=\"line\">3</span><br><span class=\"line\">4</span><br><span class=\"line\">5</span><br><span class=\"line\">6</span><br><span class=\"line\">7</span><br><span class=\"line\">8</span><br><span class=\"line\">9</span><br><span class=\"line\">10</span><br><span class=\"line\">11</span><br><span class=\"line\">12</span><br></pre></td><td class=\"code\"><pre><span class=\"line\"><span class=\"comment\"># Dockerfile 正确配置</span></span><br><span class=\"line\"><span class=\"keyword\">FROM</span> python:<span class=\"number\">3.9</span>-slim</span><br><span class=\"line\"></span><br><span class=\"line\"><span class=\"keyword\">RUN</span><span class=\"language-bash\"> apt-get update &amp;&amp; apt-get install -y \\</span></span><br><span class=\"line\"><span class=\"language-bash\">    libgl1 \\</span></span><br><span class=\"line\"><span class=\"language-bash\">    libglib2.0-0 \\</span></span><br><span class=\"line\"><span class=\"language-bash\">    gcc \\</span></span><br><span class=\"line\"><span class=\"language-bash\">    &amp;&amp; <span class=\"built_in\">rm</span> -rf /var/lib/apt/lists/*</span></span><br><span class=\"line\"></span><br><span class=\"line\"><span class=\"keyword\">WORKDIR</span><span class=\"language-bash\"> /app</span></span><br><span class=\"line\"><span class=\"keyword\">COPY</span><span class=\"language-bash\"> requirements.txt .</span></span><br><span class=\"line\"><span class=\"keyword\">RUN</span><span class=\"language-bash\"> pip install --no-cache-dir -r requirements.txt</span></span><br></pre></td></tr></table></figure>\n<h3 id=\"4-2-敏感信息泄露\">4.2 敏感信息泄露</h3>\n<p><strong>问题现象</strong>：密码等敏感信息出现在日志中</p>\n<p><strong>解决方案</strong>：使用 GitHub Secrets 管理敏感数据</p>\n<figure class=\"highlight yaml\"><table><tr><td class=\"gutter\"><pre><span class=\"line\">1</span><br><span class=\"line\">2</span><br><span class=\"line\">3</span><br><span class=\"line\">4</span><br><span class=\"line\">5</span><br><span class=\"line\">6</span><br></pre></td><td class=\"code\"><pre><span class=\"line\"><span class=\"comment\"># 在 GitHub Secrets 中配置以下变量</span></span><br><span class=\"line\"><span class=\"comment\"># DOCKER_USER, DOCKER_TOKEN, SSH_HOST, SSH_USER, SSH_PRIVATE_KEY</span></span><br><span class=\"line\"></span><br><span class=\"line\"><span class=\"comment\"># 在 workflow 中引用</span></span><br><span class=\"line\"><span class=\"attr\">env:</span></span><br><span class=\"line\">  <span class=\"attr\">DATABASE_URL:</span> <span class=\"string\">$&#123;&#123;</span> <span class=\"string\">secrets.DATABASE_URL</span> <span class=\"string\">&#125;&#125;</span></span><br></pre></td></tr></table></figure>\n<h3 id=\"4-3-构建时间过长\">4.3 构建时间过长</h3>\n<p><strong>优化方案</strong>：启用缓存机制</p>\n<figure class=\"highlight yaml\"><table><tr><td class=\"gutter\"><pre><span class=\"line\">1</span><br><span class=\"line\">2</span><br><span class=\"line\">3</span><br><span class=\"line\">4</span><br><span class=\"line\">5</span><br><span class=\"line\">6</span><br><span class=\"line\">7</span><br><span class=\"line\">8</span><br><span class=\"line\">9</span><br></pre></td><td class=\"code\"><pre><span class=\"line\"><span class=\"bullet\">-</span> <span class=\"attr\">name:</span> <span class=\"string\">Cache</span> <span class=\"string\">pip</span> <span class=\"string\">dependencies</span></span><br><span class=\"line\">  <span class=\"attr\">uses:</span> <span class=\"string\">actions/cache@v4</span></span><br><span class=\"line\">  <span class=\"attr\">with:</span></span><br><span class=\"line\">    <span class=\"attr\">path:</span> <span class=\"string\">|</span></span><br><span class=\"line\"><span class=\"string\">      ~/.cache/pip</span></span><br><span class=\"line\"><span class=\"string\">      **/__pycache__</span></span><br><span class=\"line\"><span class=\"string\"></span>    <span class=\"attr\">key:</span> <span class=\"string\">$&#123;&#123;</span> <span class=\"string\">runner.os</span> <span class=\"string\">&#125;&#125;-python-$&#123;&#123;</span> <span class=\"string\">matrix.python-version</span> <span class=\"string\">&#125;&#125;-$&#123;&#123;</span> <span class=\"string\">hashFiles(&#x27;requirements.txt&#x27;)</span> <span class=\"string\">&#125;&#125;</span></span><br><span class=\"line\">    <span class=\"attr\">restore-keys:</span> <span class=\"string\">|</span></span><br><span class=\"line\">      <span class=\"string\">$&#123;&#123;</span> <span class=\"string\">runner.os</span> <span class=\"string\">&#125;&#125;-python-$&#123;&#123;</span> <span class=\"string\">matrix.python-version</span> <span class=\"string\">&#125;&#125;-</span></span><br></pre></td></tr></table></figure>\n<hr>\n<h2 id=\"五、日志分析与调试\">五、日志分析与调试</h2>\n<h3 id=\"5-1-日志访问路径\">5.1 日志访问路径</h3>\n<figure class=\"highlight plaintext\"><table><tr><td class=\"gutter\"><pre><span class=\"line\">1</span><br></pre></td><td class=\"code\"><pre><span class=\"line\">GitHub Repository → Actions → 选择 Workflow → 选择 Run → 查看 Job 日志</span><br></pre></td></tr></table></figure>\n<h3 id=\"5-2-常见错误码\">5.2 常见错误码</h3>\n<table>\n<thead>\n<tr>\n<th style=\"text-align:left\">错误码</th>\n<th style=\"text-align:left\">含义</th>\n<th style=\"text-align:left\">排查方向</th>\n</tr>\n</thead>\n<tbody>\n<tr>\n<td style=\"text-align:left\"><code>exit code 1</code></td>\n<td style=\"text-align:left\">命令执行失败</td>\n<td style=\"text-align:left\">检查脚本语法和依赖</td>\n</tr>\n<tr>\n<td style=\"text-align:left\"><code>exit code 137</code></td>\n<td style=\"text-align:left\">内存不足</td>\n<td style=\"text-align:left\">增加 Runner 资源或优化代码</td>\n</tr>\n<tr>\n<td style=\"text-align:left\"><code>Connection refused</code></td>\n<td style=\"text-align:left\">网络连接失败</td>\n<td style=\"text-align:left\">检查网络策略和目标服务状态</td>\n</tr>\n</tbody>\n</table>\n<h3 id=\"5-3-调试技巧\">5.3 调试技巧</h3>\n<ol>\n<li>使用 <code>set -x</code> 启用命令调试</li>\n<li>添加 <code>echo</code> 输出关键变量值</li>\n<li>使用 <code>tmate</code> 进行交互式调试</li>\n</ol>\n<hr>\n<h2 id=\"六、运行效果示例\">六、运行效果示例</h2>\n<h3 id=\"6-1-成功执行效果\">6.1 成功执行效果</h3>\n<p>当工作流成功执行时，GitHub Actions 会显示以下状态：</p>\n<p><strong>Actions 页面概览</strong>：</p>\n<figure class=\"highlight plaintext\"><table><tr><td class=\"gutter\"><pre><span class=\"line\">1</span><br><span class=\"line\">2</span><br><span class=\"line\">3</span><br><span class=\"line\">4</span><br><span class=\"line\">5</span><br><span class=\"line\">6</span><br><span class=\"line\">7</span><br><span class=\"line\">8</span><br></pre></td><td class=\"code\"><pre><span class=\"line\">✓ AI-Project-CI</span><br><span class=\"line\">  push · main</span><br><span class=\"line\">  1 hour ago · in 2m 35s</span><br><span class=\"line\">  </span><br><span class=\"line\">  Jobs:</span><br><span class=\"line\">    ✅ build-and-test (Python 3.9)</span><br><span class=\"line\">    ✅ build-and-test (Python 3.10)  </span><br><span class=\"line\">    ✅ deploy</span><br></pre></td></tr></table></figure>\n<p><strong>测试步骤输出示例</strong>：</p>\n<figure class=\"highlight plaintext\"><table><tr><td class=\"gutter\"><pre><span class=\"line\">1</span><br><span class=\"line\">2</span><br><span class=\"line\">3</span><br><span class=\"line\">4</span><br><span class=\"line\">5</span><br><span class=\"line\">6</span><br><span class=\"line\">7</span><br><span class=\"line\">8</span><br><span class=\"line\">9</span><br><span class=\"line\">10</span><br><span class=\"line\">11</span><br><span class=\"line\">12</span><br><span class=\"line\">13</span><br><span class=\"line\">14</span><br><span class=\"line\">15</span><br><span class=\"line\">16</span><br><span class=\"line\">17</span><br><span class=\"line\">18</span><br><span class=\"line\">19</span><br><span class=\"line\">20</span><br><span class=\"line\">21</span><br><span class=\"line\">22</span><br><span class=\"line\">23</span><br></pre></td><td class=\"code\"><pre><span class=\"line\">Run pytest tests/unit/ -v --cov=src/</span><br><span class=\"line\">============================= test session starts ==============================</span><br><span class=\"line\">platform linux -- Python 3.9.17, pytest-7.4.0, pluggy</span><br><span class=\"line\">rootdir: /home/runner/work/anime-detect/anime-detect</span><br><span class=\"line\">collected 24 items</span><br><span class=\"line\"></span><br><span class=\"line\">tests/unit/test_detect.py::test_load_model PASSED                       [  4%]</span><br><span class=\"line\">tests/unit/test_detect.py::test_image_preprocess PASSED                  [  8%]</span><br><span class=\"line\">tests/unit/test_detect.py::test_detect_anime PASSED                      [ 12%]</span><br><span class=\"line\">...</span><br><span class=\"line\">tests/unit/test_api.py::test_health_check PASSED                         [ 95%]</span><br><span class=\"line\">tests/unit/test_api.py::test_inference_endpoint PASSED                   [100%]</span><br><span class=\"line\"></span><br><span class=\"line\">---------- coverage: platform linux, python 3.9.17-final-0 ----------</span><br><span class=\"line\">Name                      Stmts   Miss  Cover</span><br><span class=\"line\">---------------------------------------------</span><br><span class=\"line\">src/detect.py               120      5    96%</span><br><span class=\"line\">src/api.py                   85      3    96%</span><br><span class=\"line\">src/utils.py                 45      0   100%</span><br><span class=\"line\">---------------------------------------------</span><br><span class=\"line\">TOTAL                       250      8    97%</span><br><span class=\"line\"></span><br><span class=\"line\">============================= 24 passed in 15.23s ==============================</span><br></pre></td></tr></table></figure>\n<p><strong>Docker 构建输出示例</strong>：</p>\n<figure class=\"highlight plaintext\"><table><tr><td class=\"gutter\"><pre><span class=\"line\">1</span><br><span class=\"line\">2</span><br><span class=\"line\">3</span><br><span class=\"line\">4</span><br><span class=\"line\">5</span><br><span class=\"line\">6</span><br><span class=\"line\">7</span><br><span class=\"line\">8</span><br><span class=\"line\">9</span><br><span class=\"line\">10</span><br><span class=\"line\">11</span><br><span class=\"line\">12</span><br><span class=\"line\">13</span><br><span class=\"line\">14</span><br><span class=\"line\">15</span><br><span class=\"line\">16</span><br><span class=\"line\">17</span><br><span class=\"line\">18</span><br><span class=\"line\">19</span><br><span class=\"line\">20</span><br><span class=\"line\">21</span><br></pre></td><td class=\"code\"><pre><span class=\"line\">Run docker build . -t registry.example.com/anime-detect:abc123</span><br><span class=\"line\">Sending build context to Docker daemon  156.2MB</span><br><span class=\"line\"></span><br><span class=\"line\">Step 1/6 : FROM python:3.9-slim</span><br><span class=\"line\"> ---&gt; 8a955d570e80</span><br><span class=\"line\">Step 2/6 : RUN apt-get update &amp;&amp; apt-get install -y libgl1 libglib2.0-0 gcc</span><br><span class=\"line\"> ---&gt; Using cache</span><br><span class=\"line\"> ---&gt; abc123456789</span><br><span class=\"line\">Step 3/6 : WORKDIR /app</span><br><span class=\"line\"> ---&gt; Using cache</span><br><span class=\"line\"> ---&gt; def098765432</span><br><span class=\"line\">Step 4/6 : COPY requirements.txt .</span><br><span class=\"line\"> ---&gt; Using cache</span><br><span class=\"line\"> ---&gt; 123456789abc</span><br><span class=\"line\">Step 5/6 : RUN pip install --no-cache-dir -r requirements.txt</span><br><span class=\"line\"> ---&gt; Using cache</span><br><span class=\"line\"> ---&gt; 987654321def</span><br><span class=\"line\">Step 6/6 : COPY . .</span><br><span class=\"line\"> ---&gt; 0123456789ab</span><br><span class=\"line\">Successfully built 0123456789ab</span><br><span class=\"line\">Successfully tagged registry.example.com/anime-detect:abc123</span><br></pre></td></tr></table></figure>\n<h3 id=\"6-2-失败执行效果\">6.2 失败执行效果</h3>\n<p><strong>测试失败示例</strong>：</p>\n<figure class=\"highlight plaintext\"><table><tr><td class=\"gutter\"><pre><span class=\"line\">1</span><br><span class=\"line\">2</span><br><span class=\"line\">3</span><br><span class=\"line\">4</span><br><span class=\"line\">5</span><br><span class=\"line\">6</span><br><span class=\"line\">7</span><br><span class=\"line\">8</span><br><span class=\"line\">9</span><br><span class=\"line\">10</span><br><span class=\"line\">11</span><br><span class=\"line\">12</span><br><span class=\"line\">13</span><br><span class=\"line\">14</span><br><span class=\"line\">15</span><br><span class=\"line\">16</span><br><span class=\"line\">17</span><br><span class=\"line\">18</span><br></pre></td><td class=\"code\"><pre><span class=\"line\">Run pytest tests/unit/ -v --cov=src/</span><br><span class=\"line\">...</span><br><span class=\"line\">tests/unit/test_detect.py::test_detect_anime FAILED                     [ 12%]</span><br><span class=\"line\"></span><br><span class=\"line\">=================================== FAILURES ===================================</span><br><span class=\"line\">___________________________ test_detect_anime ___________________________</span><br><span class=\"line\"></span><br><span class=\"line\">def test_detect_anime():</span><br><span class=\"line\">    model = load_model()</span><br><span class=\"line\">    result = model.predict(test_image)</span><br><span class=\"line\">    </span><br><span class=\"line\">&gt;   assert result[&#x27;confidence&#x27;] &gt; 0.9</span><br><span class=\"line\">E   AssertionError: assert 0.85 &gt; 0.9</span><br><span class=\"line\">E    +  where 0.85 = &#123;&#x27;label&#x27;: &#x27;Sailor Moon&#x27;, &#x27;confidence&#x27;: 0.85&#125;[&#x27;confidence&#x27;]</span><br><span class=\"line\"></span><br><span class=\"line\">tests/unit/test_detect.py:23: AssertionError</span><br><span class=\"line\">============================= 1 failed, 23 passed in 14.87s ======================</span><br><span class=\"line\">Error: Process completed with exit code 1</span><br></pre></td></tr></table></figure>\n<p><strong>依赖安装失败示例</strong>：</p>\n<figure class=\"highlight plaintext\"><table><tr><td class=\"gutter\"><pre><span class=\"line\">1</span><br><span class=\"line\">2</span><br><span class=\"line\">3</span><br><span class=\"line\">4</span><br><span class=\"line\">5</span><br><span class=\"line\">6</span><br><span class=\"line\">7</span><br><span class=\"line\">8</span><br><span class=\"line\">9</span><br><span class=\"line\">10</span><br><span class=\"line\">11</span><br><span class=\"line\">12</span><br><span class=\"line\">13</span><br><span class=\"line\">14</span><br><span class=\"line\">15</span><br><span class=\"line\">16</span><br><span class=\"line\">17</span><br><span class=\"line\">18</span><br><span class=\"line\">19</span><br><span class=\"line\">20</span><br></pre></td><td class=\"code\"><pre><span class=\"line\">Run pip install -r requirements.txt</span><br><span class=\"line\">Collecting torch==2.0.1</span><br><span class=\"line\">  Downloading torch-2.0.1-cp39-none-linux_x86_64.whl (172.3 MB)</span><br><span class=\"line\">     ━━━━━━━━━━━━━━━━━━━━━━━━━━━━━━━━━━━━━━━━━━━━━━━━━━━━ 172.3/172.3 MB 45.2 MB/s</span><br><span class=\"line\">Collecting opencv-python==4.7.0.72</span><br><span class=\"line\">  Downloading opencv-python-4.7.0.72.tar.gz (88.3 MB)</span><br><span class=\"line\">     ━━━━━━━━━━━━━━━━━━━━━━━━━━━━━━━━━━━━━━━━━━━━━━━━━━━━ 88.3/88.3 MB 42.1 MB/s</span><br><span class=\"line\">  Installing build dependencies ... done</span><br><span class=\"line\">  Getting requirements to build wheel ... done</span><br><span class=\"line\">  Preparing metadata (pyproject.toml) ... error</span><br><span class=\"line\">  error: subprocess-exited-with-error</span><br><span class=\"line\">  </span><br><span class=\"line\">  × Preparing metadata (pyproject.toml) did not run successfully.</span><br><span class=\"line\">  │ exit code: 1</span><br><span class=\"line\">  ╰─&gt; [55 lines of output]</span><br><span class=\"line\">      error: OpenCV requires &#x27;numpy&gt;=1.21.2&#x27; but you have numpy 1.19.5 installed.</span><br><span class=\"line\">      [end of output]</span><br><span class=\"line\">  </span><br><span class=\"line\">  note: This error originates from a subprocess, and is likely not a problem with pip.</span><br><span class=\"line\">Error: Process completed with exit code 1</span><br></pre></td></tr></table></figure>\n<h3 id=\"6-3-时间统计示例\">6.3 时间统计示例</h3>\n<table>\n<thead>\n<tr>\n<th style=\"text-align:left\">步骤</th>\n<th style=\"text-align:left\">耗时</th>\n<th style=\"text-align:left\">状态</th>\n</tr>\n</thead>\n<tbody>\n<tr>\n<td style=\"text-align:left\">Checkout code</td>\n<td style=\"text-align:left\">15s</td>\n<td style=\"text-align:left\">✅</td>\n</tr>\n<tr>\n<td style=\"text-align:left\">Set up Python</td>\n<td style=\"text-align:left\">8s</td>\n<td style=\"text-align:left\">✅</td>\n</tr>\n<tr>\n<td style=\"text-align:left\">Install dependencies</td>\n<td style=\"text-align:left\">45s</td>\n<td style=\"text-align:left\">✅</td>\n</tr>\n<tr>\n<td style=\"text-align:left\">Run unit tests</td>\n<td style=\"text-align:left\">1min 20s</td>\n<td style=\"text-align:left\">✅</td>\n</tr>\n<tr>\n<td style=\"text-align:left\">Build Docker image</td>\n<td style=\"text-align:left\">3min 10s</td>\n<td style=\"text-align:left\">✅</td>\n</tr>\n<tr>\n<td style=\"text-align:left\">Deploy to production</td>\n<td style=\"text-align:left\">45s</td>\n<td style=\"text-align:left\">✅</td>\n</tr>\n<tr>\n<td style=\"text-align:left\"><strong>总计</strong></td>\n<td style=\"text-align:left\"><strong>5min 43s</strong></td>\n<td style=\"text-align:left\"><strong>✅</strong></td>\n</tr>\n</tbody>\n</table>\n<hr>\n<h2 id=\"七、进阶配置\">七、进阶配置</h2>\n<h3 id=\"7-1-多环境部署\">7.1 多环境部署</h3>\n<figure class=\"highlight yaml\"><table><tr><td class=\"gutter\"><pre><span class=\"line\">1</span><br><span class=\"line\">2</span><br><span class=\"line\">3</span><br><span class=\"line\">4</span><br><span class=\"line\">5</span><br><span class=\"line\">6</span><br><span class=\"line\">7</span><br><span class=\"line\">8</span><br><span class=\"line\">9</span><br><span class=\"line\">10</span><br><span class=\"line\">11</span><br><span class=\"line\">12</span><br></pre></td><td class=\"code\"><pre><span class=\"line\"><span class=\"attr\">jobs:</span></span><br><span class=\"line\">  <span class=\"attr\">deploy-staging:</span></span><br><span class=\"line\">    <span class=\"attr\">runs-on:</span> <span class=\"string\">ubuntu-latest</span></span><br><span class=\"line\">    <span class=\"attr\">environment:</span> <span class=\"string\">staging</span></span><br><span class=\"line\">    <span class=\"attr\">steps:</span> [<span class=\"string\">...</span>]</span><br><span class=\"line\"></span><br><span class=\"line\">  <span class=\"attr\">deploy-production:</span></span><br><span class=\"line\">    <span class=\"attr\">needs:</span> <span class=\"string\">deploy-staging</span></span><br><span class=\"line\">    <span class=\"attr\">runs-on:</span> <span class=\"string\">ubuntu-latest</span></span><br><span class=\"line\">    <span class=\"attr\">environment:</span> <span class=\"string\">production</span></span><br><span class=\"line\">    <span class=\"attr\">environment_url:</span> <span class=\"string\">https://api.example.com</span></span><br><span class=\"line\">    <span class=\"attr\">steps:</span> [<span class=\"string\">...</span>]</span><br></pre></td></tr></table></figure>\n<h3 id=\"6-2-定时任务\">6.2 定时任务</h3>\n<figure class=\"highlight yaml\"><table><tr><td class=\"gutter\"><pre><span class=\"line\">1</span><br><span class=\"line\">2</span><br><span class=\"line\">3</span><br></pre></td><td class=\"code\"><pre><span class=\"line\"><span class=\"attr\">on:</span></span><br><span class=\"line\">  <span class=\"attr\">schedule:</span></span><br><span class=\"line\">    <span class=\"bullet\">-</span> <span class=\"attr\">cron:</span> <span class=\"string\">&#x27;0 2 * * *&#x27;</span>  <span class=\"comment\"># 每天凌晨 2 点执行</span></span><br></pre></td></tr></table></figure>\n<h3 id=\"6-3-矩阵构建\">6.3 矩阵构建</h3>\n<figure class=\"highlight yaml\"><table><tr><td class=\"gutter\"><pre><span class=\"line\">1</span><br><span class=\"line\">2</span><br><span class=\"line\">3</span><br><span class=\"line\">4</span><br></pre></td><td class=\"code\"><pre><span class=\"line\"><span class=\"attr\">strategy:</span></span><br><span class=\"line\">  <span class=\"attr\">matrix:</span></span><br><span class=\"line\">    <span class=\"attr\">os:</span> [<span class=\"string\">ubuntu-latest</span>, <span class=\"string\">windows-latest</span>]</span><br><span class=\"line\">    <span class=\"attr\">python-version:</span> [<span class=\"string\">&quot;3.9&quot;</span>, <span class=\"string\">&quot;3.10&quot;</span>, <span class=\"string\">&quot;3.11&quot;</span>]</span><br></pre></td></tr></table></figure>\n<hr>\n<h2 id=\"七、最佳实践\">七、最佳实践</h2>\n<ol>\n<li><strong>分层设计</strong>：将测试、构建、部署分离为独立 Job</li>\n<li><strong>环境隔离</strong>：使用 Environment 功能管理不同部署环境</li>\n<li><strong>安全优先</strong>：所有敏感信息通过 Secrets 管理</li>\n<li><strong>缓存优化</strong>：合理使用缓存减少重复操作</li>\n<li><strong>失败通知</strong>：配置 Slack/钉钉等即时通知</li>\n<li><strong>权限最小化</strong>：限制 GitHub Token 权限范围</li>\n</ol>\n<hr>\n<h2 id=\"总结\">总结</h2>\n<p>GitHub Actions 提供了强大的自动化能力，通过合理配置可以实现从代码提交到生产部署的全流程自动化。关键在于理解组件模型、掌握配置语法，并结合项目特点进行优化。</p>\n<hr>\n<p>参考链接：</p>\n<ul>\n<li><a href=\"https://docs.github.com/en/actions\">GitHub Actions 官方文档</a></li>\n<li><a href=\"https://github.com/marketplace?type=actions\">GitHub Actions 市场</a></li>\n</ul>\n","categories":[],"tags":[{"name":"GitHub Actions","path":"api/tags/GitHub Actions.json"},{"name":"CI/CD","path":"api/tags/CI/CD.json"},{"name":"DevOps","path":"api/tags/DevOps.json"},{"name":"自动化部署","path":"api/tags/自动化部署.json"}]}